odoo/addons/stock_location_route_description/README.rst
odoo/addons/stock_location_route_description/__init__.py
odoo/addons/stock_location_route_description/__manifest__.py
odoo/addons/stock_location_route_description/i18n/stock_location_route_description.pot
odoo/addons/stock_location_route_description/models/__init__.py
odoo/addons/stock_location_route_description/models/stock_location_route.py
odoo/addons/stock_location_route_description/readme/CONTRIBUTORS.rst
odoo/addons/stock_location_route_description/readme/DESCRIPTION.rst
odoo/addons/stock_location_route_description/static/description/icon.png
odoo/addons/stock_location_route_description/static/description/index.html
odoo/addons/stock_location_route_description/tests/__init__.py
odoo/addons/stock_location_route_description/tests/test_stock_location_route_description.py
odoo/addons/stock_location_route_description/views/stock_location_route_views.xml
odoo13_addon_stock_location_route_description-13.0.1.0.1.dist-info/METADATA
odoo13_addon_stock_location_route_description-13.0.1.0.1.dist-info/WHEEL
odoo13_addon_stock_location_route_description-13.0.1.0.1.dist-info/top_level.txt
odoo13_addon_stock_location_route_description-13.0.1.0.1.dist-info/RECORD
